float_adder.v
module float_adder(num1, num2, result, overflow, zero, NaN, precisionLost, clk);
  //Ports
  input [15:0] num1, num2;
  input clk; //clock signal
  output reg [15:0] result;
  output overflow; //overflow flag
  output zero; //zero flag
  output NaN; //Not a Number flag
  output reg precisionLost;
  wire [15:0] resultt;
  //Reassing numbers as big and small
  reg [15:0] bigNum, smallNum; //to seperate big and small numbers
  //Decode big and small number
  wire [9:0] big_fra, small_fra; //to hold fraction part
  wire [4:0] big_ex_pre, small_ex_pre;
  wire [4:0] big_ex, small_ex; //to hold exponent part
  wire big_sig, small_sig; //to hold signs
  wire [10:0] big_float, small_float; //to hold as float number with integer
  reg [10:0] sign_small_float, shifted_small_float; //preparing small float
  wire [4:0] ex_diff; //difrence between exponentials
  reg [9:0] sum_shifted; //Shift fraction part of sum
  reg [3:0] shift_am;
  wire neg_exp;
  //Extensions for higher precision
  reg [9:0] small_extension;
  wire [9:0] sum_extension;

  wire [10:0] sum; //sum of numbers with integer parts
  wire sum_carry;
  wire sameSign;
  wire zeroSmall;
  wire inf_num; //at least on of the operands is inf.

  wire [4:0] res_exp_same_s, res_exp_diff_s;
  
  //Flags
  assign zero = (num1[14:0] == num2[14:0]) & (~num1[15] == num2[15]);
  assign overflow = ((&big_ex[4:1] & ~big_ex[0]) & sum_carry & sameSign) | inf_num;
  assign NaN = (&num1[14:10] & |num1[9:0]) | (&num2[14:10] & |num2[9:0]);
  assign inf_num = (&num1[14:10] & ~|num1[9:0]) | (&num2[14:10] & ~|num2[9:0]); //check for infinate number
  
  //Get result
  assign resultt[15] = big_sig; //result sign same as big sign
  assign res_exp_same_s = big_ex + {4'd0, (~zeroSmall & sum_carry & sameSign)} - {4'd0,({1'b0,result[9:0]} == sum)};
  assign res_exp_diff_s = (neg_exp | (shift_am == 4'd10)) ? 5'd0 : (~shift_am + big_ex + 5'd1);
  assign resultt[14:10] = ((sameSign) ? res_exp_same_s : res_exp_diff_s) | {5{overflow}}; //result exponent
  assign resultt[9:0] = ((zeroSmall) ? big_fra : ((sameSign) ? ((sum_carry) ? sum[10:1] : sum[9:0]) : ((neg_exp) ? 10'd0 : sum_shifted))) & {10{~overflow}};

  //decode numbers
  assign {big_sig, big_ex_pre, big_fra} = bigNum;
  assign {small_sig, small_ex_pre, small_fra} = smallNum;
  assign sameSign = (big_sig == small_sig);
  assign zeroSmall = ~(|small_ex | |small_fra);
  assign big_ex = big_ex_pre + {4'd0, ~|big_ex_pre};
  assign small_ex = small_ex_pre + {4'd0, ~|small_ex_pre};

  //add integer parts
  assign big_float = {|big_ex_pre, big_fra};
  assign small_float = {|small_ex_pre, small_fra};
  assign ex_diff = big_ex - small_ex; //diffrence between exponents
  assign {sum_carry, sum} = sign_small_float + big_float; //add numbers
  assign sum_extension = small_extension;

  //Get shift amount for subtraction
  assign neg_exp = (big_ex < shift_am);

  always @(posedge clk)
    result <= resultt; //assign result on clock edge

  always@(*)
    begin
      casex(sum)
        11'b1xxxxxxxxxx: shift_am = 4'd0;
        11'b01xxxxxxxxx: shift_am = 4'd1;
        11'b001xxxxxxxx: shift_am = 4'd2;
        11'b0001xxxxxxx: shift_am = 4'd3;
        11'b00001xxxxxx: shift_am = 4'd4;
        11'b000001xxxxx: shift_am = 4'd5;
        11'b0000001xxxx: shift_am = 4'd6;
        11'b00000001xxx: shift_am = 4'd7;
        11'b000000001xx: shift_am = 4'd8;
        11'b0000000001x: shift_am = 4'd9;
        default: shift_am = 4'd10;
      endcase
    end

  //Shift result for sub.
  always@(*) 
    begin
      case (shift_am)
        4'd0: sum_shifted =  sum[9:0];
        4'd1: sum_shifted = {sum[8:0],sum_extension[9]};
        4'd2: sum_shifted = {sum[7:0],sum_extension[9:8]};
        4'd3: sum_shifted = {sum[6:0],sum_extension[9:7]};
        4'd4: sum_shifted = {sum[5:0],sum_extension[9:6]};
        4'd5: sum_shifted = {sum[4:0],sum_extension[9:5]};
        4'd6: sum_shifted = {sum[3:0],sum_extension[9:4]};
        4'd7: sum_shifted = {sum[2:0],sum_extension[9:3]};
        4'd8: sum_shifted = {sum[1:0],sum_extension[9:2]};
        4'd9: sum_shifted = {sum[0],  sum_extension[9:1]};
        default: sum_shifted = sum_extension;
      endcase
      case (shift_am)
        4'd0: precisionLost = |sum_extension;
        4'd1: precisionLost = |sum_extension[8:0];
        4'd2: precisionLost = |sum_extension[7:0];
        4'd3: precisionLost = |sum_extension[6:0];
        4'd4: precisionLost = |sum_extension[5:0];
        4'd5: precisionLost = |sum_extension[4:0];
        4'd6: precisionLost = |sum_extension[3:0];
        4'd7: precisionLost = |sum_extension[2:0];
        4'd8: precisionLost = |sum_extension[1:0];
        4'd9: precisionLost = |sum_extension[0];
        default: precisionLost = 1'b0;
      endcase
    end

  //take small number to exponent of big number
  always@(*) 
    begin
      case (ex_diff)
        5'h0: {shifted_small_float,small_extension} = {small_float,10'd0};
        5'h1: {shifted_small_float,small_extension} = {small_float,9'd0};
        5'h2: {shifted_small_float,small_extension} = {small_float,8'd0};
        5'h3: {shifted_small_float,small_extension} = {small_float,7'd0};
        5'h4: {shifted_small_float,small_extension} = {small_float,6'd0};
        5'h5: {shifted_small_float,small_extension} = {small_float,5'd0};
        5'h6: {shifted_small_float,small_extension} = {small_float,4'd0};
        5'h7: {shifted_small_float,small_extension} = {small_float,3'd0};
        5'h8: {shifted_small_float,small_extension} = {small_float,2'd0};
        5'h9: {shifted_small_float,small_extension} = {small_float,1'd0};
        5'ha: {shifted_small_float,small_extension} = small_float;
        5'hb: {shifted_small_float,small_extension} = small_float[10:1];
        5'hc: {shifted_small_float,small_extension} = small_float[10:2];
        5'hd: {shifted_small_float,small_extension} = small_float[10:3];
        5'he: {shifted_small_float,small_extension} = small_float[10:4];
        5'hf: {shifted_small_float,small_extension} = small_float[10:5];
        5'h10: {shifted_small_float,small_extension} = small_float[10:5];
        5'h11: {shifted_small_float,small_extension} = small_float[10:6];
        5'h12: {shifted_small_float,small_extension} = small_float[10:7];
        5'h13: {shifted_small_float,small_extension} = small_float[10:8];
        5'h14: {shifted_small_float,small_extension} = small_float[10:9];
        5'h15: {shifted_small_float,small_extension} = small_float[10];
        5'h16: {shifted_small_float,small_extension} = 0;
      endcase
    end

  always@(*) //if signs are diffrent take 2s compliment of small number
    begin
      if(sameSign)
        begin
          sign_small_float = shifted_small_float;
        end
      else
        begin
          sign_small_float = ~shifted_small_float + 11'b1;
        end
    end

  always@(*) //determine big number
    begin
      if(num2[14:10] > num1[14:10])
        begin
          bigNum = num2;
          smallNum = num1;
        end
      else if(num2[14:10] == num1[14:10])
        begin
          if(num2[9:0] > num1[9:0])
            begin
              bigNum = num2;
              smallNum = num1;
            end
          else
            begin
              bigNum = num1;
              smallNum = num2;
            end
        end
      else
        begin
          bigNum = num1;
          smallNum = num2;
        end
    end
endmodule

fp_adder_tb.v
`timescale 1ns / 1ps
//`include "Sources/adder-multiplier.v"

module flpa_sim();
  reg [9:0] fra1, fra2;
  reg sign1, sign2;
  reg [4:0] exp1, exp2;
  reg clk; // Clock signal for the adder
    initial clk = 0;
  wire [15:0] result, num1, num2;
  wire overflow, zero;
  wire [9:0] res_fra, expected_fra;
  wire res_sign, nan, precisionLost, expected_sign;
  wire [4:0] res_exp, expected_exp;

  assign {res_sign, res_exp, res_fra} = result;
  assign num1 = {sign1, exp1, fra1};
  assign num2 = {sign2, exp2, fra2};

  float_adder uut(num1, num2, result, overflow, zero, nan, precisionLost, clk);

  wire correct;
  reg [15:0] result_expected;

  assign correct = (result_expected == result);
  assign {expected_sign,expected_exp,expected_fra} = result_expected;

  initial
    begin
        $dumpfile("outputs/adder.vcd");
        $dumpvars(1, flpa_sim);
    
        {sign1, exp1, fra1} = 16'hb9a8; // -0.707
        {sign2, exp2, fra2} = 16'hc03e; // -2.121
        result_expected = 16'hc1a8; // -2.828
        #100
        {sign1, exp1, fra1} = 16'hc03e; // -2.121
        {sign2, exp2, fra2} = 16'h39a8; // 0.707
        result_expected = 16'hbda8; // -1.414
        #100

        {sign1, exp1, fra1} = 16'hc200; // -3
        {sign2, exp2, fra2} = 16'hc1a8; // -2.828
        result_expected = 16'hc5d4; // -5.828    
        #100

        {sign1, exp1, fra1} = 16'hbc00; // -1
        {sign2, exp2, fra2} = 16'hbda8; // -1.414
        result_expected = 16'hc0d4; // - 2.414
        
    //   //Bug
    //   {sign1, exp1, fra1} = 16'hc0b0;
    //   {sign2, exp2, fra2} = 16'h1cc0;
    //   result_expected = 16'hc0ae;
    //   #100
    //   {sign1, exp1, fra1} = 16'h00e0;
    //   {sign2, exp2, fra2} = 16'h5060;
    //   result_expected = 16'h5060;
    //   #100
    //   {sign1, exp1, fra1} = 16'h29a8;
    //   {sign2, exp2, fra2} = 16'he1f9;
    //   result_expected = 16'he1f9;
    //   #100
    //   {sign1, exp1, fra1} = 16'h54a5;
    //   {sign2, exp2, fra2} = 16'h1cc0;
    //   result_expected = 16'h54a5;
    //   #100
    //   {sign1, exp1, fra1} = 16'h00b8;
    //   {sign2, exp2, fra2} = 16'h0080;
    //   result_expected = 16'h0138;
    //   #100
    //   //Addition with precision lost
    //   sign1 = 0;
    //   sign2 = 0;
    //   exp1 = 21;
    //   exp2 = 14;
    //   fra1 = 10'b10100101;
    //   fra2 = 10'b11001100;
    //   result_expected = 16'h54ae;
    //   #100
    //   //Addition of two numbers with same exp
    //   sign1 = 0;
    //   sign2 = 0;
    //   exp1 = 4;
    //   exp2 = 4;
    //   fra1 = 10'b10100000;
    //   fra2 = 10'b01101100;
    //   result_expected = 16'h1486;
    //   #100
    //   //Addition without precision lost
    //   sign1 = 0;
    //   sign2 = 0;
    //   exp1 = 10;
    //   exp2 = 12;
    //   fra1 = 10'b11100000;
    //   fra2 = 10'b01101001;
    //   result_expected = 16'h31a1;
    //   #100
    //   //Addition diffrent signs without precision lost
    //   sign1 = 0;
    //   sign2 = 1;
    //   exp1 = 5;
    //   exp2 = 6;
    //   fra1 = 10'b10101100;
    //   fra2 = 10'b00101101;
    //   result_expected = 16'h935c;
    //   #100
    //   //Addition diffrent signs without precision lost
    //   sign1 = 1;
    //   sign2 = 0;
    //   exp1 = 13;
    //   exp2 = 13;
    //   fra1 = 10'b00001100;
    //   fra2 = 10'b11101100;
    //   result_expected = 16'h2b00;
    //   #100
    //   //Addition diffrent signs without precision lost
    //   sign1 = 1;
    //   sign2 = 0;
    //   exp1 = 30;
    //   exp2 = 30;
    //   fra1 = 10'b10101010;
    //   fra2 = 10'b10101100;
    //   result_expected = 16'h5400;
    //   #100
    //   //Zero flag
    //   sign1 = 1;
    //   sign2 = 0;
    //   exp1 = 25;
    //   exp2 = 25;
    //   fra1 = 10'b10011101;
    //   fra2 = 10'b10011101;
    //   result_expected = 16'h8000;
    //   #100
    //   //nan flag
    //   sign1 = 0;
    //   sign2 = 0;
    //   exp1 = 5'b10001;
    //   exp2 = 5'b11111;
    //   fra1 = 10'b11111111;
    //   fra2 = 10'b11111111;
    //   result_expected = 16'h7cff;
    //   #100
    //   //Overflow flag
    //   sign1 = 0;
    //   sign2 = 0;
    //   exp1 = 5'b11110;
    //   exp2 = 5'b11110;
    //   fra1 = 10'b1111111111;
    //   fra2 = 10'b1111111111;
    //   result_expected = 16'h7c00;
    //   #100
    //   //Overflow flag
    //   sign1 = 0;
    //   sign2 = 0;
    //   exp1 = 5'b11111;
    //   exp2 = 5'b10010;
    //   fra1 = 10'b0000000000;
    //   fra2 = 10'b1110000011;
    //   result_expected = 16'h7c00;

        // Wait for a while to observe results
        #100;
        
        // Finish simulation
        $finish;
    end

    always #5 clk = ~clk; // Generate clock
endmodule

adder.vcd
$date
	Wed Jun 18 20:10:39 2025
$end
$version
	Icarus Verilog
$end
$timescale
	1ps
$end
$scope module flpa_sim $end
$var wire 1 ! correct $end
$var wire 5 " expected_exp [4:0] $end
$var wire 10 # expected_fra [9:0] $end
$var wire 1 $ expected_sign $end
$var wire 1 % nan $end
$var wire 16 & num1 [15:0] $end
$var wire 16 ' num2 [15:0] $end
$var wire 1 ( overflow $end
$var wire 1 ) precisionLost $end
$var wire 5 * res_exp [4:0] $end
$var wire 10 + res_fra [9:0] $end
$var wire 1 , res_sign $end
$var wire 16 - result [15:0] $end
$var wire 1 . zero $end
$var reg 1 / clk $end
$var reg 5 0 exp1 [4:0] $end
$var reg 5 1 exp2 [4:0] $end
$var reg 10 2 fra1 [9:0] $end
$var reg 10 3 fra2 [9:0] $end
$var reg 16 4 result_expected [15:0] $end
$var reg 1 5 sign1 $end
$var reg 1 6 sign2 $end
$upscope $end
$enddefinitions $end
#0
$dumpvars
16
15
b1100000110101000 4
b111110 3
b110101000 2
b10000 1
b1110 0
0/
0.
bx -
x,
bx +
bx *
0)
0(
b1100000000111110 '
b1011100110101000 &
0%
1$
b110101000 #
b10000 "
x!
$end
#5000
1,
b10000 *
b110101000 +
1!
b1100000110101000 -
1/
#10000
0/
#15000
1/
#20000
0/
#25000
1/
#30000
0/
#35000
1/
#40000
0/
#45000
1/
#50000
0/
#55000
1/
#60000
0/
#65000
1/
#70000
0/
#75000
1/
#80000
0/
#85000
1/
#90000
0/
#95000
1/
#100000
b1111 "
0/
b1011110110101000 4
0!
06
b1110 1
b110101000 3
b11100110101000 '
b10000 0
b111110 2
b1100000000111110 &
#105000
b1111 *
1!
b1011110110101000 -
1/
#110000
0/
#115000
1/
#120000
0/
#125000
1/
#130000
0/
#135000
1/
#140000
0/
#145000
1/
#150000
0/
#155000
1/
#160000
0/
#165000
1/
#170000
0/
#175000
1/
#180000
0/
#185000
1/
#190000
0/
#195000
1/
#200000
b10001 "
b111010100 #
0/
b1100010111010100 4
0!
16
b10000 1
b1100000110101000 '
b1000000000 2
b1100001000000000 &
#205000
b10001 *
b111010100 +
1!
b1100010111010100 -
1/
#210000
0/
#215000
1/
#220000
0/
#225000
1/
#230000
0/
#235000
1/
#240000
0/
#245000
1/
#250000
0/
#255000
1/
#260000
0/
#265000
1/
#270000
0/
#275000
1/
#280000
0/
#285000
1/
#290000
0/
#295000
1/
#300000
b10000 "
b11010100 #
0/
b1100000011010100 4
0!
b1111 1
b1011110110101000 '
b1111 0
b0 2
b1011110000000000 &
#305000
b10000 *
b11010100 +
1!
b1100000011010100 -
1/
