float_multi.v
module float_multi(num1, num2, result, overflow, zero, NaN, precisionLost, clk);
  //Operands
  input [15:0] num1, num2;
  input clk; //clock signal
  output reg [15:0] result;
  wire [15:0] resultt; 
  //Flags
  output overflow;//overflow flag
  output zero; //zero flag
  output NaN; //Not a Number flag
  output precisionLost;
  //Decode numbers
  wire sign1, sign2, signR; //hold signs
  wire [4:0] ex1, ex2, exR; //hold exponents
  wire [4:0] ex1_pre, ex2_pre, exR_calc; //hold exponents
  reg [4:0] exSubCor;
  wire [4:0] exSum_fault;
  wire ex_cannot_correct;
  wire [9:0] fra1, fra2, fraR; //hold fractions
  reg [9:0] fraSub, fraSub_corrected;
  wire [20:0] float1;
  wire [10:0] float2;
  wire exSum_sign;
  wire [6:0] exSum;
  wire [5:0] exSum_prebais, exSum_abs; //exponent sum
  wire [11:0] float_res, float_res_preround; //result
  wire [9:0] float_res_fra;
  wire [9:0] dump_res; //Lost precision
  reg [21:0] res_full;
  wire [21:0] res_full_preshift;
  reg [20:0] mid[10:0];
  wire inf_num; //at least on of the operands is inf.
  wire subNormal;
  wire zero_num_in, zero_calculated;

  //Partial flags
  assign zero_num_in = ~(|num1[14:0] & |num2[14:0]);
  assign zero_calculated = (subNormal & (fraSub == 10'd0)) | (exSum_sign & (~|res_full[20:11]));
  assign ex_cannot_correct = {1'b0,exSubCor} > exSum_abs; //?: or >=

  //Flags
  assign zero = zero_num_in | zero_calculated;
  assign NaN = (&num1[14:10] & |num1[9:0]) | (&num2[14:10] & |num2[9:0]) | (zero_num_in & inf_num); //check for NaN 
  assign inf_num = (&num1[14:10] & ~|num1[9:0]) | (&num2[14:10] & ~|num2[9:0]); //check for infinite number
  assign overflow = inf_num | (~exSum[6] & exSum[5]);
  assign subNormal = ~|float_res[11:10];
  assign precisionLost = |dump_res | (exSum_prebais < 6'd15);
  
  //decode-encode numbers
  assign {sign1, ex1_pre, fra1} = num1;
  assign {sign2, ex2_pre, fra2} = num2;
  assign ex1 = ex1_pre + {4'd0, ~|ex1_pre};
  assign ex2 = ex2_pre + {4'd0, ~|ex2_pre};
  assign resultt = {signR, exR, fraR};
  
  always @(posedge clk)
    result <= resultt; //assign result on clock edge

  //exponentials are added
  assign exSum = exSum_prebais - 7'd15;
  assign exSum_prebais = {1'b0,ex1} + {1'b0,ex2};
  assign exSum_abs = (exSum_sign) ? (~exSum[5:0] + 6'd1) : exSum[5:0];
  assign exSum_sign = exSum[6];

  //Get floating numbers
  assign float1 = {|ex1_pre, fra1, 10'd0};
  assign float2 = {|ex2_pre, fra2};

  //Calculate result
  assign signR = (sign1 ^ sign2);
  assign exR_calc = exSum[4:0] + {4'd0, float_res[11]} + (~exSubCor & {5{subNormal}}) + {4'd0, subNormal};
  assign exR = NaN ? 5'b11111 : (exR_calc | {5{overflow}}) & {5{~(zero | exSum_sign | ex_cannot_correct)}};
  assign fraR = NaN ? 10'b11111111 : ((exSum_sign) ? res_full[20:11] :((subNormal) ? fraSub_corrected : float_res_fra)) & {10{~(zero | overflow)}} ;
  assign float_res_fra = (float_res[11]) ? float_res[10:1] : float_res[9:0];
  assign float_res = float_res_preround + {10'd0,dump_res[9]}; // possibly generates wrong result due to overflow
  assign {float_res_preround, dump_res} = res_full_preshift;
  assign res_full_preshift = mid[0] + mid[1] + mid[2] + mid[3] + mid[4] + mid[5] + mid[6] + mid[7] + mid[8] + mid[9] + mid[10];
  assign exSum_fault = exSubCor - exSum_abs[4:0];
  always@(*)
    begin
      if(exSum_sign)
        case(exSum_abs)
          6'h0: res_full = res_full_preshift;
          6'h1: res_full = (res_full_preshift >> 1);
          6'h2: res_full = (res_full_preshift >> 2);
          6'h3: res_full = (res_full_preshift >> 3);
          6'h4: res_full = (res_full_preshift >> 4);
          6'h5: res_full = (res_full_preshift >> 5);
          6'h6: res_full = (res_full_preshift >> 6);
          6'h7: res_full = (res_full_preshift >> 7);
          6'h8: res_full = (res_full_preshift >> 8);
          6'h9: res_full = (res_full_preshift >> 9);
          6'ha: res_full = (res_full_preshift >> 10);
          6'hb: res_full = (res_full_preshift >> 11);
          6'hc: res_full = (res_full_preshift >> 12);
          6'hd: res_full = (res_full_preshift >> 13);
          6'he: res_full = (res_full_preshift >> 14);
          6'hf: res_full = (res_full_preshift >> 15);
          default: res_full = (res_full_preshift >> 16);
        endcase
      else
        res_full = res_full_preshift;
    end
  always@(*)
    begin
      if(ex_cannot_correct)
        case(exSum_fault)
          5'h0: fraSub_corrected = fraSub;
          5'h1: fraSub_corrected = (fraSub >> 1);
          5'h2: fraSub_corrected = (fraSub >> 2);
          5'h3: fraSub_corrected = (fraSub >> 3);
          5'h4: fraSub_corrected = (fraSub >> 4);
          5'h5: fraSub_corrected = (fraSub >> 5);
          5'h6: fraSub_corrected = (fraSub >> 6);
          5'h7: fraSub_corrected = (fraSub >> 7);
          5'h8: fraSub_corrected = (fraSub >> 8);
          5'h9: fraSub_corrected = (fraSub >> 9);
          default: fraSub_corrected = 10'h0;
        endcase
      else
        fraSub_corrected = fraSub;
    end

  always@(*) //create mids from fractions
    begin
      mid[0] = (float1 >> 10) & {21{float2[0]}};
      mid[1] = (float1 >> 9)  & {21{float2[1]}};
      mid[2] = (float1 >> 8)  & {21{float2[2]}};
      mid[3] = (float1 >> 7)  & {21{float2[3]}};
      mid[4] = (float1 >> 6)  & {21{float2[4]}};
      mid[5] = (float1 >> 5)  & {21{float2[5]}};
      mid[6] = (float1 >> 4)  & {21{float2[6]}};
      mid[7] = (float1 >> 3)  & {21{float2[7]}};
      mid[8] = (float1 >> 2)  & {21{float2[8]}};
      mid[9] = (float1 >> 1)  & {21{float2[9]}};
      mid[10] = float1        & {21{float2[10]}};
    end
  //Corrections for subnormal normal op
  always@(*)
    begin
      casex(res_full)
        22'b001xxxxxxxxxxxxxxxxxxx:
          begin
            fraSub = res_full[18:9];
          end
        22'b0001xxxxxxxxxxxxxxxxxx:
          begin
            fraSub = res_full[17:8];
          end
        22'b00001xxxxxxxxxxxxxxxxx:
          begin
            fraSub = res_full[16:7];
          end
        22'b000001xxxxxxxxxxxxxxxx:
          begin
            fraSub = res_full[15:6];
          end
        22'b0000001xxxxxxxxxxxxxxx:
          begin
            fraSub = res_full[14:5];
          end
        22'b00000001xxxxxxxxxxxxxx:
          begin
            fraSub = res_full[13:4];
          end
        22'b000000001xxxxxxxxxxxxx:
          begin
            fraSub = res_full[12:3];
          end
        22'b0000000001xxxxxxxxxxxx:
          begin
            fraSub = res_full[11:2];
          end
        22'b00000000001xxxxxxxxxxx:
          begin
            fraSub = res_full[10:1];
          end
        22'b000000000001xxxxxxxxxx:
          begin
            fraSub = res_full[9:0];
          end
        22'b0000000000001xxxxxxxxx:
          begin
            fraSub = {res_full[8:0], 1'd0};
          end
        22'b00000000000001xxxxxxxx:
          begin
            fraSub = {res_full[7:0], 2'd0};
          end
        22'b000000000000001xxxxxxx:
          begin
            fraSub = {res_full[6:0], 3'd0};
          end
        22'b0000000000000001xxxxxx:
          begin
            fraSub = {res_full[5:0], 4'd0};
          end
        22'b00000000000000001xxxxx:
          begin
            fraSub = {res_full[4:0], 5'd0};
          end
        22'b000000000000000001xxxx:
          begin
            fraSub = {res_full[3:0], 6'd0};
          end
        22'b0000000000000000001xxx:
          begin
            fraSub = {res_full[2:0], 7'd0};
          end
        22'b00000000000000000001xx:
          begin
            fraSub = {res_full[1:0], 8'd0};
          end
        22'b000000000000000000001x:
          begin
            fraSub = {res_full[0], 9'd0};
          end
        default:
          begin
            fraSub = 10'd0;
          end
      endcase
    end
  always@(*)
    begin
      casex(res_full)
        22'b001xxxxxxxxxxxxxxxxxxx:
          begin
            exSubCor = 5'd1;
          end
        22'b0001xxxxxxxxxxxxxxxxxx:
          begin
            exSubCor = 5'd2;
          end
        22'b00001xxxxxxxxxxxxxxxxx:
          begin
            exSubCor = 5'd3;
          end
        22'b000001xxxxxxxxxxxxxxxx:
          begin
            exSubCor = 5'd4;
          end
        22'b0000001xxxxxxxxxxxxxxx:
          begin
            exSubCor = 5'd5;
          end
        22'b00000001xxxxxxxxxxxxxx:
          begin
            exSubCor = 5'd6;
          end
        22'b000000001xxxxxxxxxxxxx:
          begin
            exSubCor = 5'd7;
          end
        22'b0000000001xxxxxxxxxxxx:
          begin
            exSubCor = 5'd8;
          end
        22'b00000000001xxxxxxxxxxx:
          begin
            exSubCor = 5'd9;
          end
        22'b000000000001xxxxxxxxxx:
          begin
            exSubCor = 5'd10;
          end
        22'b0000000000001xxxxxxxxx:
          begin
            exSubCor = 5'd11;
          end
        22'b00000000000001xxxxxxxx:
          begin
            exSubCor = 5'd12;
          end
        22'b000000000000001xxxxxxx:
          begin
            exSubCor = 5'd13;
          end
        22'b0000000000000001xxxxxx:
          begin
            exSubCor = 5'd14;
          end
        22'b00000000000000001xxxxx:
          begin
            exSubCor = 5'd15;
          end
        22'b000000000000000001xxxx:
          begin
            exSubCor = 5'd16;
          end
        22'b0000000000000000001xxx:
          begin
            exSubCor = 5'd17;
          end
        22'b00000000000000000001xx:
          begin
            exSubCor = 5'd18;
          end
        22'b000000000000000000001x:
          begin
            exSubCor = 5'd19;
          end
        default:
          begin
            exSubCor = 5'd0;
          end
      endcase
    end
endmodule

fp_multi_tb.v
`timescale 1ns / 1ps
// `include "Sources/adder-multiplier.v"

module flpm_sim();
  reg [9:0] fra1, fra2;
  reg sign1, sign2;
  reg [4:0] exp1, exp2;
  reg clk; // Clock signal for the multiplier
    initial clk = 0; // Initialize clock signal
  wire [15:0] result, num1, num2;
  wire overflow, zero, precisionLost;
  wire [9:0] res_fra, expected_fra;
  wire res_sign, nan, expected_sign;
  wire [4:0] res_exp, expected_exp;
  reg [15:0] result_expected;

  assign {res_sign, res_exp, res_fra} = result;
  assign num1 = {sign1, exp1, fra1};
  assign num2 = {sign2, exp2, fra2};

  float_multi uut(num1, num2, result, overflow, zero, nan, precisionLost, clk);
  wire correct;

  assign correct = result == result_expected;
  assign {expected_sign,expected_exp,expected_fra} = result_expected;

  initial
    begin
        $dumpfile("multi.vcd");
        $dumpvars(1, flpm_sim);
        
        {sign1, exp1, fra1} = 16'hc200; // -3
        {sign2, exp2, fra2} = 16'hb9a8; // -0.707
        result_expected = 16'h403e; // 2.121
        #100

        {sign1, exp1, fra1} = 16'hbc00; // -1
        {sign2, exp2, fra2} = 16'h39a8; // 0.707
        result_expected = 16'hb9a8; // -0.707
        #100

        {sign1, exp1, fra1} = 16'hbc00; // -1
        {sign2, exp2, fra2} = 16'hb9a8; // -0.707
        result_expected = 16'h39a8; // 0.707
        #100

        {sign1, exp1, fra1} = 16'hc200; // -3
        {sign2, exp2, fra2} = 16'h39a8; // 0.707
        result_expected = 16'hc03e; // - 2.121

        //Buggy cases
    //   {sign1, exp1, fra1} = 16'h4689;
    //   {sign2, exp2, fra2} = 16'h0025;
    //   result_expected = 16'h00f2;
    //   #100
    //   {sign1, exp1, fra1} = 16'h4489;
    //   {sign2, exp2, fra2} = 16'h001d;
    //   result_expected = 16'h0084;
    //   #100
    //   {sign1, exp1, fra1} = 16'h1234;
    //   {sign2, exp2, fra2} = 16'h9876;
    //   result_expected = 16'h801b;
    //   #100
    //   {sign1, exp1, fra1} = 16'h8216;
    //   {sign2, exp2, fra2} = 16'h20be;
    //   result_expected = 16'h8004;
    //   #100
    //   //Multipcation with precision lost
    //   sign1 = 0;
    //   sign2 = 0;
    //   exp1 = 21;
    //   exp2 = 4;
    //   fra1 = 10'b10100101;
    //   fra2 = 10'b11001100;
    //   result_expected = 16'h2992;
    //   #100
    //   //Multipcation without precision lost
    //   sign1 = 0;
    //   sign2 = 0;
    //   exp1 = 4;
    //   exp2 = 4;
    //   fra1 = 10'b10100000;
    //   fra2 = 10'b01100000;
    //   result_expected = 16'h5;
    //   #100
    //   //Multipcation without precision lost diffrent signs
    //   sign1 = 1;
    //   sign2 = 0;
    //   exp1 = 16;
    //   exp2 = 7;
    //   fra1 = 10'b10110000;
    //   fra2 = 10'b11000000;
    //   result_expected = 16'ha191;
    //   #100
    //   //Multipcation with Zero
    //   sign1 = 0;
    //   sign2 = 0;
    //   exp1 = 16;
    //   exp2 = 0;
    //   fra1 = 10'b10110000;
    //   fra2 = 10'b00000000;
    //   result_expected = 16'h0;
    //   #100
    //   //Multipcation with Infinite
    //   sign1 = 0;
    //   sign2 = 0;
    //   exp1 = 16;
    //   exp2 = 5'b11111;
    //   fra1 = 10'b10110000;
    //   fra2 = 10'b00000000;
    //   result_expected = 16'h7c00;
    //   #100
    //   //Overflow
    //   sign1 = 0;
    //   sign2 = 0;
    //   exp1 = 16;
    //   exp2 = 20;
    //   fra1 = 10'b10110000;
    //   fra2 = 10'b01011000;
    //   result_expected = 16'h5517;
    //   #100
    //   //Multipcation of 1 subnormal, 1 normal
    //   sign1 = 0;
    //   sign2 = 0;
    //   exp1 = 0;
    //   exp2 = 20;
    //   fra1 = 10'b11100000;
    //   fra2 = 10'b01100000;
    //   result_expected = 16'hfa8;
    //   #100
    //   //Multipcation of 2 subnormal
    //   sign1 = 0;
    //   sign2 = 0;
    //   exp1 = 0;
    //   exp2 = 0;
    //   fra1 = 10'b10111000;
    //   fra2 = 10'b10000000;
    //   result_expected = 16'h0;
    //   #100

    //   //Multiplication with NaN
    //   sign1 = 0;
    //   sign2 = 0;
    //   exp1 = 5'b01101;
    //   exp2 = 5'b11111;
    //   fra1 = 10'b10100111;
    //   fra2 = 10'b11111111;
    //   result_expected = 16'h7cff;
    //   #100

    //   //Multiplication of two negative numbers
    //   sign1 = 1;
    //   sign2 = 1;
    //   exp1 = 5'b11011;
    //   exp2 = 5'b01010;
    //   fra1 = 10'b0111111001;
    //   fra2 = 10'b1010111000;
    //   result_expected = 16'h5d04;
    //   #100

    //   //Multiplication of zero and infinite
    //   sign1 = 1;
    //   sign2 = 0;
    //   exp1 = 5'b11111;
    //   exp2 = 5'b00000;
    //   fra1 = 10'b0000000000;
    //   fra2 = 10'b0000000000;
    //   result_expected = 16'hfcff;
        #100 $finish;
    end


    always #5 clk = ~clk; // Generate clock
endmodule

multi.vcd
$date
	Wed Jun 18 20:12:13 2025
$end
$version
	Icarus Verilog
$end
$timescale
	1ps
$end
$scope module flpm_sim $end
$var wire 1 ! correct $end
$var wire 5 " expected_exp [4:0] $end
$var wire 10 # expected_fra [9:0] $end
$var wire 1 $ expected_sign $end
$var wire 1 % nan $end
$var wire 16 & num1 [15:0] $end
$var wire 16 ' num2 [15:0] $end
$var wire 1 ( overflow $end
$var wire 1 ) precisionLost $end
$var wire 5 * res_exp [4:0] $end
$var wire 10 + res_fra [9:0] $end
$var wire 1 , res_sign $end
$var wire 16 - result [15:0] $end
$var wire 1 . zero $end
$var reg 1 / clk $end
$var reg 5 0 exp1 [4:0] $end
$var reg 5 1 exp2 [4:0] $end
$var reg 10 2 fra1 [9:0] $end
$var reg 10 3 fra2 [9:0] $end
$var reg 16 4 result_expected [15:0] $end
$var reg 1 5 sign1 $end
$var reg 1 6 sign2 $end
$upscope $end
$enddefinitions $end
#0
$dumpvars
16
15
b100000000111110 4
b110101000 3
b1000000000 2
b1110 1
b10000 0
0/
0.
bx -
x,
bx +
bx *
0)
0(
b1011100110101000 '
b1100001000000000 &
0%
0$
b111110 #
b10000 "
x!
$end
#5000
0,
b10000 *
b111110 +
1!
b100000000111110 -
1/
#10000
0/
#15000
1/
#20000
0/
#25000
1/
#30000
0/
#35000
1/
#40000
0/
#45000
1/
#50000
0/
#55000
1/
#60000
0/
#65000
1/
#70000
0/
#75000
1/
#80000
0/
#85000
1/
#90000
0/
#95000
1/
#100000
1$
b1110 "
b110101000 #
0/
b1011100110101000 4
0!
06
b11100110101000 '
b1111 0
b0 2
b1011110000000000 &
#105000
1,
b1110 *
b110101000 +
1!
b1011100110101000 -
1/
#110000
0/
#115000
1/
#120000
0/
#125000
1/
#130000
0/
#135000
1/
#140000
0/
#145000
1/
#150000
0/
#155000
1/
#160000
0/
#165000
1/
#170000
0/
#175000
1/
#180000
0/
#185000
1/
#190000
0/
#195000
1/
#200000
0$
0/
b11100110101000 4
0!
16
b1011100110101000 '
#205000
0,
1!
b11100110101000 -
1/
#210000
0/
#215000
1/
#220000
0/
#225000
1/
#230000
0/
#235000
1/
#240000
0/
#245000
1/
#250000
0/
#255000
1/
#260000
0/
#265000
1/
#270000
0/
#275000
1/
#280000
0/
#285000
1/
#290000
0/
#295000
1/
#300000
1$
b10000 "
b111110 #
0/
b1100000000111110 4
0!
06
b11100110101000 '
b10000 0
b1000000000 2
b1100001000000000 &
#305000
1,
b10000 *
b111110 +
1!
b1100000000111110 -
1/
