twiddleROM.v
module twiddleROM (
  input [2:0] index,
  input clk,
  output reg [15:0] Wreal, Wimag);
  
  reg [15:0] W [15:0]; // ROM declaration
  reg [3:0] add_reg; // Address Register
  
  initial
    begin // Store twiddle factor values in ROM
      // W**0
      W[4'h0] <= 16'h3c00; // 1 (Real)
      W[4'h1] <= 16'h0000; // 0 (Imaginary)
      // W**1
      W[4'h2] <= 16'h39a8; // 0.707
      W[4'h3] <= 16'hb9a8; // -0.707
      // W**2
      W[4'h4] <= 16'h0000; // 0
      W[4'h5] <= 16'hbc00; // -1
      // W**3
      W[4'h6] <= 16'hb9a8; // -0.707
      W[4'h7] <= 16'hb9a8; // -0.707
      // W**4
      W[4'h8] <= 16'hbc00; // -1
      W[4'h9] <= 16'h0000; // 0
      // W**5
      W[4'ha] <= 16'hb9a8; // -0.707
      W[4'hb] <= 16'h39a8; // 0.707
      // W**6
      W[4'hc] <= 16'h0000; // 0
      W[4'hd] <= 16'h3c00; // 1
      // W**7
      W[4'he] <= 16'h39a8; // 0.707
      W[4'hf] <= 16'h39a8; // 0.707
    end
  
  always @(posedge clk)
    add_reg <= {1'b0,index};
  
  always @(posedge clk)
    begin
        // Output corresponding W 
        Wreal <= W[2*add_reg];
        Wimag <= W[2*add_reg+1];
    end
endmodule

tROM_tb.v
`timescale 1ns/1ns

module tROM_tb;
  reg [2:0] index;
  reg en, clk;
  wire [15:0] Wreal, Wimag;

  twiddleROM dut (index, en, clk, Wreal, Wimag);

  initial begin
    $dumpfile("wave.vcd");
    $dumpvars(1,tROM_tb);

    index = 3'b000; en = 0; clk = 0;

    forever #5 clk = ~clk; // Clock Generation (10ns period)
  end

  initial begin
    // Initial state before any active clock edge or input change
    $display($time,": index = %d, en = %b, W = %h+j%h", index, en, Wreal, Wimag);

    #5 // At t=5, clk goes high (first active edge)
    en = 1'b1; index = 3'd0;
    $display($time,": index = %d, en = %b, W = %h+j%h", index, en, Wreal, Wimag);

    // Repeat loop to iterate through index values 1 to 7
    repeat (7) begin 
      #10
      index = index + 1; // Increment index 
      $display($time,": index = %d, en = %b, W = %h+j%h", index, en, Wreal, Wimag);
    end

    #10 $display($time,": index = %d, en = %b, W = %h+j%h", index, en, Wreal, Wimag);
    #10 $display($time,": index = %d, en = %b, W = %h+j%h", index, en, Wreal, Wimag);
    $finish; // End simulation
  end
endmodule

wave.vcd
$date
	Wed Jun 18 20:14:26 2025
$end
$version
	Icarus Verilog
$end
$timescale
	1ns
$end
$scope module tROM_tb $end
$var wire 16 ! Wimag [15:0] $end
$var wire 16 " Wreal [15:0] $end
$var reg 1 # clk $end
$var reg 1 $ en $end
$var reg 3 % index [2:0] $end
$upscope $end
$enddefinitions $end
#0
$dumpvars
b0 %
0$
0#
bx "
bx !
$end
#5
1$
1#
#10
0#
#15
b0 !
b11110000000000 "
1#
b1 %
#20
0#
#25
b1011100110101000 !
b11100110101000 "
1#
b10 %
#30
0#
#35
b1011110000000000 !
b0 "
1#
b11 %
#40
0#
#45
b1011100110101000 !
b1011100110101000 "
1#
b100 %
#50
0#
#55
b0 !
b1011110000000000 "
1#
b101 %
#60
0#
#65
b11100110101000 !
b1011100110101000 "
1#
b110 %
#70
0#
#75
b11110000000000 !
b0 "
1#
b111 %
#80
0#
#85
b11100110101000 !
b11100110101000 "
1#
